callnowusa/__init__.py
callnowusa/callnowusa.py
callnowusa-0.1.1.dist-info/licenses/LICENSE.txt
callnowusa-0.1.1.dist-info/METADATA
callnowusa-0.1.1.dist-info/WHEEL
callnowusa-0.1.1.dist-info/top_level.txt
callnowusa-0.1.1.dist-info/RECORD
