Metadata-Version: 2.4
Name: callnowusa
Version: 0.1.1
Summary: A client for interacting with the CallNowUSA API
Home-page: https://github.com/JishanKapoor/CallNowUsa
Author: Jishan Kapoor
Author-email: Jishan Kapoor <kapoorjishan2@gmail.com>
Project-URL: Homepage, https://github.com/JishanKapoor/CallNowUsa
Classifier: Programming Language :: Python :: 3
Classifier: License :: OSI Approved :: MIT License
Classifier: Operating System :: OS Independent
Requires-Python: >=3.7
License-File: LICENSE.txt
Requires-Dist: requests>=2.28.0
Dynamic: license-file
